{
	"groups": [
		{
			"keys": "description_json,coins_two_json,money_small_png,monster_1_png,monster_2_png,monster_3_png,stone_png,coins_four_json,coins_one_json,coins_three_json,StartUI_jpg,startBtn_png,EndGame_jpg,butns_png,butns_down_png,attract_coins_png,house_png,house2_png,house3_png,house4_png,house5_png,猫的动画导入_3_tex_png,cat_ani_tex_json,cat_ani_ske_json,cat_3_tex_png,cat_test_tex_json,cat_test_ske_json,cat_label_tex_json,cat_label_ske_json,cat_ani_tex_png,background_png,ground_png,ground_jpg,beijing_png",
			"name": "preload"
		}
	],
	"resources": [
		{
			"name": "description_json",
			"type": "json",
			"url": "config/description.json"
		},
		{
			"name": "coins_two_json",
			"type": "json",
			"url": "assets/coins_two.json"
		},
		{
			"name": "money_small_png",
			"type": "image",
			"url": "assets/money_small.png"
		},
		{
			"name": "monster_1_png",
			"type": "image",
			"url": "assets/monster_1.png"
		},
		{
			"name": "monster_2_png",
			"type": "image",
			"url": "assets/monster_2.png"
		},
		{
			"name": "monster_3_png",
			"type": "image",
			"url": "assets/monster_3.png"
		},
		{
			"name": "stone_png",
			"type": "image",
			"url": "assets/stone.png"
		},
		{
			"name": "coins_four_json",
			"type": "json",
			"url": "assets/coins_four.json"
		},
		{
			"name": "coins_one_json",
			"type": "json",
			"url": "assets/coins_one.json"
		},
		{
			"name": "coins_three_json",
			"type": "json",
			"url": "assets/coins_three.json"
		},
		{
			"name": "StartUI_jpg",
			"type": "image",
			"url": "assets/StartUI.jpg"
		},
		{
			"name": "startBtn_png",
			"type": "image",
			"url": "assets/startBtn.png"
		},
		{
			"name": "EndGame_jpg",
			"type": "image",
			"url": "assets/EndGame.jpg"
		},
		{
			"name": "butns_png",
			"type": "image",
			"url": "assets/butns.png"
		},
		{
			"name": "butns_down_png",
			"type": "image",
			"url": "assets/butns_down.png"
		},
		{
			"name": "attract_coins_png",
			"type": "image",
			"url": "assets/attract_coins.png"
		},
		{
			"name": "house_png",
			"type": "image",
			"url": "assets/house.png"
		},
		{
			"name": "house2_png",
			"type": "image",
			"url": "assets/house2.png"
		},
		{
			"name": "house3_png",
			"type": "image",
			"url": "assets/house3.png"
		},
		{
			"name": "house4_png",
			"type": "image",
			"url": "assets/house4.png"
		},
		{
			"name": "house5_png",
			"type": "image",
			"url": "assets/house5.png"
		},
		{
			"name": "猫的动画导入_3_tex_png",
			"type": "image",
			"url": "assets/猫的动画导入_3_tex.png"
		},
		{
			"name": "cat_ani_tex_json",
			"type": "json",
			"url": "assets/cat_ani_tex.json"
		},
		{
			"name": "cat_ani_ske_json",
			"type": "json",
			"url": "assets/cat_ani_ske.json"
		},
		{
			"name": "cat_3_tex_png",
			"type": "image",
			"url": "assets/cat_3_tex.png"
		},
		{
			"name": "cat_test_tex_json",
			"type": "json",
			"url": "assets/cat_test_tex.json"
		},
		{
			"name": "cat_test_ske_json",
			"type": "json",
			"url": "assets/cat_test_ske.json"
		},
		{
			"name": "cat_label_tex_json",
			"type": "json",
			"url": "assets/cat_label_tex.json"
		},
		{
			"name": "cat_label_ske_json",
			"type": "json",
			"url": "assets/cat_label_ske.json"
		},
		{
			"name": "cat_ani_tex_png",
			"type": "image",
			"url": "assets/cat_ani_tex.png"
		},
		{
			"name": "background_png",
			"type": "image",
			"url": "assets/background.png"
		},
		{
			"name": "ground_png",
			"type": "image",
			"url": "assets/ground.png"
		},
		{
			"name": "ground_jpg",
			"type": "image",
			"url": "assets/ground.jpg"
		},
		{
			"name": "beijing_png",
			"type": "image",
			"url": "assets/beijing.png"
		}
	]
}